iris_webhooks_module/IrisWebHooksConfig.py
iris_webhooks_module/IrisWebHooksInterface.py
iris_webhooks_module/__init__.py
iris_webhooks_module-1.0.1.dist-info/LICENSE.txt
iris_webhooks_module-1.0.1.dist-info/METADATA
iris_webhooks_module-1.0.1.dist-info/WHEEL
iris_webhooks_module-1.0.1.dist-info/top_level.txt
iris_webhooks_module-1.0.1.dist-info/RECORD
