Metadata-Version: 2.1
Name: iris-webhooks-module
Version: 1.0.1
Summary: An interface module for webhooks support in DFIR-IRIS
Home-page: https://github.com/dfir-iris/iris-webhooks-module
Author: DFIR-IRIS
Author-email: contact@dfir-iris.org
License: UNKNOWN
Platform: UNKNOWN
Classifier: Programming Language :: Python :: 3
Classifier: License :: OSI Approved :: GNU Lesser General Public License v3 (LGPLv3)
Classifier: Operating System :: OS Independent
License-File: LICENSE.txt
